graphs2go/__init__.py
graphs2go/assets/__init__.py
graphs2go/assets/build_cypher_files_asset.py
graphs2go/assets/build_direct_rdf_file_asset.py
graphs2go/assets/build_direct_rdf_graph_asset.py
graphs2go/assets/build_interchange_file_asset.py
graphs2go/assets/build_postgres_database_asset.py
graphs2go/assets/build_skos_file_asset.py
graphs2go/assets/build_skos_graph_asset.py
graphs2go/assets/rdf_file_asset_defaults.py
graphs2go/loaders/__init__.py
graphs2go/loaders/buffering_rdf_loader.py
graphs2go/loaders/cypher_directory_loader.py
graphs2go/loaders/directory_loader.py
graphs2go/loaders/rdf_directory_loader.py
graphs2go/loaders/rdf_loader.py
graphs2go/models/__init__.py
graphs2go/models/compression_method.py
graphs2go/models/cypher/__init__.py
graphs2go/models/cypher/create_node_statement.py
graphs2go/models/cypher/create_relationship_statement.py
graphs2go/models/cypher/node_pattern.py
graphs2go/models/cypher/properties.py
graphs2go/models/cypher/property_value.py
graphs2go/models/cypher/statement.py
graphs2go/models/interchange/__init__.py
graphs2go/models/interchange/graph.py
graphs2go/models/interchange/label.py
graphs2go/models/interchange/model.py
graphs2go/models/interchange/node.py
graphs2go/models/interchange/property.py
graphs2go/models/interchange/relationship.py
graphs2go/models/label_type.py
graphs2go/models/postgres/__init__.py
graphs2go/models/postgres/database.py
graphs2go/models/postgres/schema.py
graphs2go/models/postgres/table.py
graphs2go/models/postgres/tables.py
graphs2go/models/rdf/__init__.py
graphs2go/models/rdf/file_format.py
graphs2go/models/rdf/format.py
graphs2go/models/rdf/graph.py
graphs2go/models/rdf/model.py
graphs2go/models/rdf/named_model.py
graphs2go/models/rdf/named_resource.py
graphs2go/models/rdf/resource.py
graphs2go/models/skos/__init__.py
graphs2go/models/skos/concept.py
graphs2go/models/skos/concept_scheme.py
graphs2go/models/skos/graph.py
graphs2go/models/skos/label.py
graphs2go/models/skos/labeled_model.py
graphs2go-1.0.2.dist-info/LICENSE
graphs2go-1.0.2.dist-info/METADATA
graphs2go-1.0.2.dist-info/WHEEL
graphs2go-1.0.2.dist-info/RECORD
